setup.py
algopy/__init__.py
algopy/q60.py
algopy/q62.py
algopy/q63.py
algopy/q64.py
algopy/q67.py
algopy/q70.py
algopy/q71.py
algopy/q73.py
algopy/q75.py
algopy/q78.py
algopy/q81.py
algopy/q84.py
algopy_ucas.egg-info/PKG-INFO
algopy_ucas.egg-info/SOURCES.txt
algopy_ucas.egg-info/dependency_links.txt
algopy_ucas.egg-info/requires.txt
algopy_ucas.egg-info/top_level.txt